glchat_sdk/__init__.py
glchat_sdk/chatbots.py
glchat_sdk/client.py
glchat_sdk/conversation.py
glchat_sdk/message.py
glchat_sdk/models.py
glchat_sdk/py.typed
glchat_sdk/auth/__init__.py
glchat_sdk/auth/api.py
glchat_sdk/auth/whatsapp.py
glchat_sdk/evals/README.md
glchat_sdk/evals/__init__.py
glchat_sdk/evals/config.py
glchat_sdk/evals/constant.py
glchat_sdk/evals/evaluate_glchat.py
glchat_sdk/evals/inference.py
glchat_sdk/evals/resource_manager.py
glchat_sdk/evals/simple_glchat_qa_dataset.py
glchat_sdk/evals/dataset_example/glchat_qa_data.csv
glchat_sdk/evals/utils/__init__.py
glchat_sdk/evals/utils/glchat_utils.py
glchat_sdk/evals_outputs/leaderboard.csv
glchat_sdk/users/__init__.py
glchat_sdk/users/api.py
glchat_sdk/users/verification/__init__.py
glchat_sdk/users/verification/api.py
glchat_sdk/users/verification/username.py
glchat_sdk-0.0.11.dist-info/METADATA
glchat_sdk-0.0.11.dist-info/WHEEL
glchat_sdk-0.0.11.dist-info/licenses/LICENSE
glchat_sdk-0.0.11.dist-info/RECORD
