Metadata-Version: 2.4
Name: glchat-sdk
Version: 0.0.11
Summary: GLChat Python Client
Author-email: GDP Labs <jobs@gdplabs.id>
License-File: LICENSE
Requires-Python: >=3.11
Requires-Dist: httpx>=0.28.1
Requires-Dist: pydantic>=2.0.0
Provides-Extra: evals
Requires-Dist: aioboto3<16.0.0,>=15.2.0; extra == 'evals'
Requires-Dist: gllm-core-binary<0.4.0,>=0.3.0; (python_version < '3.14') and extra == 'evals'
Requires-Dist: gllm-evals-binary[deepeval,langchain,ragas]<0.0.32,>=0.0.31; (python_version < '3.14') and extra == 'evals'
Requires-Dist: langfuse<4.0.0,>=3.2.1; (python_version < '3.14') and extra == 'evals'
Requires-Dist: pytest-asyncio<0.24.0,>=0.23.6; extra == 'evals'
